snowstorm/__init__.py
snowstorm/consts.py
snowstorm/exceptions.py
snowstorm/request/__init__.py
snowstorm/request/core/__init__.py
snowstorm/request/core/base.py
snowstorm/request/core/delete.py
snowstorm/request/core/get.py
snowstorm/request/core/patch.py
snowstorm/request/core/post.py
snowstorm/request/helpers/__init__.py
snowstorm/request/helpers/create.py
snowstorm/request/helpers/delete.py
snowstorm/request/helpers/read.py
snowstorm/request/helpers/stream.py
snowstorm/request/helpers/update.py
snowstorm/resource/__init__.py
snowstorm/resource/fields/__init__.py
snowstorm/resource/fields/base.py
snowstorm/resource/fields/boolean.py
snowstorm/resource/fields/choice.py
snowstorm/resource/fields/datetime.py
snowstorm/resource/fields/email.py
snowstorm/resource/fields/nested.py
snowstorm/resource/fields/numeric.py
snowstorm/resource/fields/reference.py
snowstorm/resource/fields/text.py
snowstorm/resource/query/__init__.py
snowstorm/resource/query/builder.py
snowstorm/resource/query/operators.py
snowstorm/resource/query/segment.py
snowstorm/resource/query/utils.py
snowstorm/resource/schema.py
snowstorm/response/__init__.py
snowstorm/response/schemas.py
snowstorm-0.0.1.dist-info/LICENSE
snowstorm-0.0.1.dist-info/WHEEL
snowstorm-0.0.1.dist-info/METADATA
snowstorm-0.0.1.dist-info/RECORD
